<?xml version="1.0" encoding="utf-8" ?>
<dwsync>
<file name="Dogs-Are.png" server="107.180.0.87/public_html/" local="133426324030499743" remote="133434715200000000" />
<file name="Fall-is-Here.png" server="107.180.0.87/public_html/" local="133426323223605836" remote="133435570200000000" />
<file name="Saving-the-Little-Joys-in-Life.png" server="107.180.0.87/public_html/" local="133426320348352260" remote="133436593800000000" />
<file name="My-Have-Monsters-Sure-Changed-Since-I-was-a-Kid.png" server="107.180.0.87/public_html/" local="133436913497228697" remote="133437319800000000" />
<file name="Screwy-Mouse.png" server="107.180.0.87/public_html/" local="133436912434785194" remote="133438248600000000" />
<file name="Its-All-Just-a-Whole-Lot-of-Sigh.png" server="107.180.0.87/public_html/" local="133436910156689664" remote="133439150400000000" />
<file name="Talk-Nice.png" server="107.180.0.87/public_html/" local="133436909327039906" remote="133439985000000000" />
<file name="Its-All-Lasagna-to-Me.png" server="107.180.0.87/public_html/" local="133436908640592644" remote="133440863400000000" />
<file name="My-Little-Spider.png" server="107.180.0.87/public_html/" local="133436907751728121" remote="133441812600000000" />
<file name="Tis-So-True.png" server="107.180.0.87/public_html/" local="133436906857618599" remote="133442591400000000" />
<file name="I-Spy-With-My-Little-Eyes.png" server="107.180.0.87/public_html/" local="133436906004537297" remote="133443412200000000" />
<file name="Go-Away-Little-Ghost.png" server="107.180.0.87/public_html/" local="133436905301812693" remote="133444253400000000" />
<file name="Cat-Horror.png" server="107.180.0.87/public_html/" local="133436903898806665" remote="133445170200000000" />
<file name="We-Dont-Need-Too-Much-of-a-Good-Thing.png" server="107.180.0.87/public_html/" local="133426319452168750" remote="133445975400000000" />
<file name="Stop-Looking-At-Me-Especially-When-I-Sleep.png" server="107.180.0.87/public_html/" local="133446085995170962" remote="133446920400000000" />
<file name="Why-Retire-From-Laziness.png" server="107.180.0.87/public_html/" local="133446084209376440" remote="133447760400000000" />
<file name="Initializing-the-Messy-Dog.png" server="107.180.0.87/public_html/" local="133446083238625741" remote="133448634000000000" />
<file name="You-Cant-Please-Everyone.png" server="107.180.0.87/public_html/" local="133446081914299271" remote="133449430200000000" />
<file name="The-ReOccurring-NightMare.png" server="107.180.0.87/public_html/" local="133446081004007151" remote="133450405200000000" />
<file name="Into-Each-Life-of-a-Tree-Some-Leaves-Must-Fall.png" server="107.180.0.87/public_html/" local="133446080223740855" remote="133451266800000000" />
<file name="UnSecreting-The-Secrets.png" server="107.180.0.87/public_html/" local="133446079167161326" remote="133452183000000000" />
<file name="Yes-Your-Chips-have-Been-CatNaped.png" server="107.180.0.87/public_html/" local="133446078032888081" remote="133452979200000000" />
<file name="Oh-You-Are-So-Barky-Arcky.png" server="107.180.0.87/public_html/" local="133446076716726587" remote="133453853400000000" />
<file name="The-Zs-Have-it.png" server="107.180.0.87/public_html/" local="133453946949533845" remote="133454713800000000" />
<file name="The-Refrigerater-Can't-Keep-a-Secret.png" server="107.180.0.87/public_html/" local="133453945713354818" remote="133455563400000000" />
<file name="Maybe-They-Ment-to-Say-Sleep-Walking.png" server="107.180.0.87/public_html/" local="133453944270005386" remote="133456428600000000" />
<file name="Poor-Little-Leaf.png" server="107.180.0.87/public_html/" local="133446074855231311" remote="133457282400000000" />
<file name="And-Just-a-Sprig-of-this-to-Fix-the-whole-Mess.png" server="107.180.0.87/public_html/" local="133426318700486746" remote="133458128400000000" />
<file name="You-Dont-See-That-EveryDay.png" server="107.180.0.87/public_html/" local="133426317678493603" remote="133459019400000000" />
<file name="Im-Calling-My-Lawyer.png" server="107.180.0.87/public_html/" local="133426316923644215" remote="133459869600000000" />
</dwsync>